points_table_simulator/__init__.py
points_table_simulator/constants.py
points_table_simulator/exceptions.py
points_table_simulator/points_table_simulator.py
points_table_simulator-2.0.1.dist-info/LICENSE
points_table_simulator-2.0.1.dist-info/METADATA
points_table_simulator-2.0.1.dist-info/WHEEL
points_table_simulator-2.0.1.dist-info/top_level.txt
points_table_simulator-2.0.1.dist-info/RECORD
