Metadata-Version: 2.1
Name: points-table-simulator
Version: 2.0.1
Summary: This package will simulate the points table based on different possible results in a sports tournament
Home-page: https://github.com/NishanthMuruganantham/points-table-simulator
Author: Nishanth Muruganantham
Author-email: nishanthmurugananth10@gmail.com
License: MIT
License-File: LICENSE
Requires-Dist: numpy
Requires-Dist: pandas
